autoplex/__init__.py
autoplex/_version.py
autoplex/settings.py
autoplex/auto/__init__.py
autoplex/auto/phonons/__init__.py
autoplex/auto/phonons/flows.py
autoplex/auto/phonons/jobs.py
autoplex/auto/rss/__init__.py
autoplex/auto/rss/flows.py
autoplex/auto/rss/jobs.py
autoplex/benchmark/__init__.py
autoplex/benchmark/phonons/__init__.py
autoplex/benchmark/phonons/flows.py
autoplex/benchmark/phonons/jobs.py
autoplex/benchmark/phonons/utils.py
autoplex/benchmark/rss/__init__.py
autoplex/data/__init__.py
autoplex/data/common/__init__.py
autoplex/data/common/flows.py
autoplex/data/common/jobs.py
autoplex/data/common/utils.py
autoplex/data/phonons/__init__.py
autoplex/data/phonons/flows.py
autoplex/data/phonons/jobs.py
autoplex/data/phonons/utils.py
autoplex/data/rss/__init__.py
autoplex/data/rss/flows.py
autoplex/data/rss/jobs.py
autoplex/data/rss/utils.py
autoplex/fitting/__init__.py
autoplex/fitting/common/__init__.py
autoplex/fitting/common/flows.py
autoplex/fitting/common/jobs.py
autoplex/fitting/common/regularization.py
autoplex/fitting/common/utils.py
autoplex/fitting/phonons/__init__.py
autoplex/fitting/rss/__init__.py
autoplex/misc/__init__.py
autoplex/misc/castep/__init__.py
autoplex/misc/castep/castep_keywords.json
autoplex/misc/castep/flows.py
autoplex/misc/castep/jobs.py
autoplex/misc/castep/run.py
autoplex/misc/castep/schema.py
autoplex/misc/castep/utils.py
autoplex/misc/utils/__init__.py
autoplex/misc/utils/mock_castep.py
autoplex-0.2.0.dist-info/licenses/LICENSE
autoplex-0.2.0.dist-info/METADATA
autoplex-0.2.0.dist-info/WHEEL
autoplex-0.2.0.dist-info/top_level.txt
autoplex-0.2.0.dist-info/RECORD
