Metadata-Version: 2.4
Name: autoplex
Version: 0.2.0
Summary: Automated machine-learned Potential Landscape explorer
Author-email: Janine George <janine.george@bam.de>
License: GPL-3.0 license
Keywords: high-throughput,automated,mlpotential
Classifier: Programming Language :: Python :: 3
Classifier: Programming Language :: Python :: 3.10
Classifier: Programming Language :: Python :: 3.11
Classifier: Development Status :: 5 - Production/Stable
Classifier: Intended Audience :: Science/Research
Classifier: Operating System :: OS Independent
Requires-Python: <3.12,>=3.10
License-File: LICENSE
Requires-Dist: pymatgen>=2024.11.13
Requires-Dist: atomate2[strict]>=0.0.21
Requires-Dist: ase==3.24.0
Requires-Dist: calorine>=3.0
Requires-Dist: matgl>=1.2.6
Requires-Dist: mace-torch>=0.3.12
Requires-Dist: numpy
Requires-Dist: lightning-utilities==0.14.3
Requires-Dist: typing
Requires-Dist: nequip
Requires-Dist: hiphive
Requires-Dist: dgl<=2.2.0; sys_platform != "linux"
Requires-Dist: dgl<=2.4; sys_platform == "linux"
Requires-Dist: torchdata<=0.7.1
Requires-Dist: torch<=2.2.0; sys_platform != "linux"
Requires-Dist: torch<=2.2.1; sys_platform == "linux"
Requires-Dist: quippy-ase==0.9.14; python_version < "3.12"
Provides-Extra: docs
Requires-Dist: autodoc_pydantic==2.2.0; extra == "docs"
Requires-Dist: ipython; extra == "docs"
Requires-Dist: jsonschema[format]; extra == "docs"
Requires-Dist: myst_parser==4.0.1; extra == "docs"
Requires-Dist: numpydoc==1.9.0; extra == "docs"
Requires-Dist: sphinx-copybutton==0.5.2; extra == "docs"
Requires-Dist: sphinx==8.1.3; extra == "docs"
Requires-Dist: sphinx_design==0.6.1; extra == "docs"
Requires-Dist: myst-nb==1.3.0; extra == "docs"
Requires-Dist: sphinx-book-theme==1.1.0; extra == "docs"
Requires-Dist: sphinxcontrib-mermaid; extra == "docs"
Requires-Dist: nbconvert==7.16.6; extra == "docs"
Provides-Extra: workflow-managers
Requires-Dist: FireWorks==2.0.4; extra == "workflow-managers"
Requires-Dist: jobflow-remote==0.1.7; extra == "workflow-managers"
Provides-Extra: strict
Requires-Dist: calorine==3.0; extra == "strict"
Requires-Dist: pymatgen==2025.2.18; extra == "strict"
Requires-Dist: atomate2[strict]==0.0.21; extra == "strict"
Requires-Dist: matgl==1.2.7; extra == "strict"
Requires-Dist: quippy-ase==0.9.14; python_version < "3.12" and extra == "strict"
Requires-Dist: ase==3.24.0; extra == "strict"
Requires-Dist: mace-torch==0.3.13; extra == "strict"
Requires-Dist: lightning-utilities==0.14.3; extra == "strict"
Requires-Dist: numpy; extra == "strict"
Requires-Dist: typing; extra == "strict"
Requires-Dist: dgl<=2.2.0; sys_platform != "linux" and extra == "strict"
Requires-Dist: dgl<=2.4; sys_platform == "linux" and extra == "strict"
Requires-Dist: torchdata<=0.7.1; extra == "strict"
Requires-Dist: torch<=2.2.0; sys_platform != "linux" and extra == "strict"
Requires-Dist: torch<=2.2.1; sys_platform == "linux" and extra == "strict"
Requires-Dist: nequip==0.6.1; extra == "strict"
Requires-Dist: hiphive==1.4; extra == "strict"
Provides-Extra: dev
Requires-Dist: pre-commit>=2.12.1; extra == "dev"
Provides-Extra: tests
Requires-Dist: pytest; extra == "tests"
Requires-Dist: pytest-mock; extra == "tests"
Requires-Dist: pytest-split; extra == "tests"
Requires-Dist: pytest-cov; extra == "tests"
Requires-Dist: types-setuptools; extra == "tests"
Requires-Dist: nbmake; extra == "tests"
Dynamic: license-file
